docsumo/Docsumo.py
docsumo/__init__.py
docsumo/config.py
docsumo/error.py
docsumo-0.5.9.dist-info/LICENSE
docsumo-0.5.9.dist-info/METADATA
docsumo-0.5.9.dist-info/WHEEL
docsumo-0.5.9.dist-info/top_level.txt
docsumo-0.5.9.dist-info/RECORD
