Metadata-Version: 2.1
Name: docsumo
Version: 0.5.9
Summary: Python client for Docsumo
Home-page: https://www.docsumo.com/
Author: Docsumo
Author-email: hello@docsumo.com
License: MIT
Classifier: Intended Audience :: Education
Classifier: Intended Audience :: Science/Research
Classifier: Intended Audience :: Developers
Classifier: License :: OSI Approved :: MIT License
Classifier: Programming Language :: Python
Classifier: Programming Language :: Python :: 3
Classifier: Topic :: Scientific/Engineering
Classifier: Topic :: Software Development
Requires-Python: >=3
License-File: LICENSE
Requires-Dist: requests
